LICENSE
MANIFEST.in
README.md
setup.cfg
setup.py
pandarallel/__init__.py
pandarallel/core.py
pandarallel/progress_bars.py
pandarallel/utils.py
pandarallel.egg-info/PKG-INFO
pandarallel.egg-info/SOURCES.txt
pandarallel.egg-info/dependency_links.txt
pandarallel.egg-info/requires.txt
pandarallel.egg-info/top_level.txt
pandarallel/data_types/__init__.py
pandarallel/data_types/dataframe.py
pandarallel/data_types/dataframe_groupby.py
pandarallel/data_types/expanding_groupby.py
pandarallel/data_types/generic.py
pandarallel/data_types/rolling_groupby.py
pandarallel/data_types/series.py
pandarallel/data_types/series_rolling.py