Metadata-Version: 2.1
Name: pandarallel
Version: 1.6.3
Summary: An easy to use library to speed up computation (by parallelizing on multi CPUs) with pandas.
Home-page: https://nalepae.github.io/pandarallel
Author: Manu NALEPA
Author-email: nalepae@gmail.com
License: BSD
Platform: UNKNOWN
Classifier: License :: OSI Approved :: BSD License
Classifier: Programming Language :: Python
Classifier: Programming Language :: Python :: 3
Classifier: Programming Language :: Python :: 3 :: Only
Classifier: Topic :: Scientific/Engineering
Provides-Extra: dev
License-File: LICENSE
